h5rdmtoolbox/__init__.py
h5rdmtoolbox/_cfg.py
h5rdmtoolbox/_repr.py
h5rdmtoolbox/_version.py
h5rdmtoolbox/cli.py
h5rdmtoolbox/consts.py
h5rdmtoolbox/errors.py
h5rdmtoolbox/identifiers.py
h5rdmtoolbox/plotting.py
h5rdmtoolbox/protected_attributes.py
h5rdmtoolbox/protocols.py
h5rdmtoolbox/tutorial.py
h5rdmtoolbox/user.py
h5rdmtoolbox/utils.py
h5rdmtoolbox/convention/__init__.py
h5rdmtoolbox/convention/cfg.py
h5rdmtoolbox/convention/consts.py
h5rdmtoolbox/convention/core.py
h5rdmtoolbox/convention/errors.py
h5rdmtoolbox/convention/generate.py
h5rdmtoolbox/convention/references.py
h5rdmtoolbox/convention/standard_attributes.py
h5rdmtoolbox/convention/toolbox_validators.py
h5rdmtoolbox/convention/utils.py
h5rdmtoolbox/convention/ontology/__init__.py
h5rdmtoolbox/convention/ontology/h5ontocls.py
h5rdmtoolbox/convention/ontology/hdf_datatypes.py
h5rdmtoolbox/data/def_icon.png
h5rdmtoolbox/data/fluid-v1.yml
h5rdmtoolbox/data/h5tbx.yaml
h5rdmtoolbox/data/id_icon.png
h5rdmtoolbox/data/iri_icon.png
h5rdmtoolbox/data/ld_icon.png
h5rdmtoolbox/data/piv-v1.yml
h5rdmtoolbox/data/style.css
h5rdmtoolbox/data/tutorial_convention.yaml
h5rdmtoolbox/data/tutorial_standard_name_table.yaml
h5rdmtoolbox/data/type_icon.png
h5rdmtoolbox/database/__init__.py
h5rdmtoolbox/database/interface.py
h5rdmtoolbox/database/lazy.py
h5rdmtoolbox/database/mongo.py
h5rdmtoolbox/database/hdfdb/__init__.py
h5rdmtoolbox/database/hdfdb/filedb.py
h5rdmtoolbox/database/hdfdb/objdb.py
h5rdmtoolbox/database/hdfdb/query.py
h5rdmtoolbox/database/hdfdb/utils.py
h5rdmtoolbox/extensions/__init__.py
h5rdmtoolbox/extensions/magnitude.py
h5rdmtoolbox/extensions/normalize.py
h5rdmtoolbox/extensions/onto.py
h5rdmtoolbox/extensions/units.py
h5rdmtoolbox/extensions/vector.py
h5rdmtoolbox/gui/__init__.py
h5rdmtoolbox/gui/fairify.py
h5rdmtoolbox/gui/src/__init__.py
h5rdmtoolbox/gui/src/main.py
h5rdmtoolbox/layout/__init__.py
h5rdmtoolbox/layout/core.py
h5rdmtoolbox/ld/__init__.py
h5rdmtoolbox/ld/globals.py
h5rdmtoolbox-2.5.4.dist-info/licenses/LICENSE
h5rdmtoolbox-2.5.4.dist-info/METADATA
h5rdmtoolbox-2.5.4.dist-info/WHEEL
h5rdmtoolbox-2.5.4.dist-info/entry_points.txt
h5rdmtoolbox-2.5.4.dist-info/top_level.txt
h5rdmtoolbox-2.5.4.dist-info/RECORD
