Metadata-Version: 2.4
Name: h5rdmtoolbox
Version: 2.5.4
Summary: Supporting a FAIR Research Data lifecycle using Python and HDF5.
Home-page: https://h5rdmtoolbox.readthedocs.io/en/latest/
Author: Matthias Probst
Author-email: matth.probst@gmail.com
Classifier: Programming Language :: Python :: 3.9
Classifier: Programming Language :: Python :: 3.10
Classifier: Programming Language :: Python :: 3.11
Classifier: Programming Language :: Python :: 3.12
Classifier: Programming Language :: Python :: 3.13
Classifier: License :: OSI Approved :: MIT License
Classifier: Operating System :: OS Independent
Classifier: Development Status :: 4 - Beta
Classifier: Topic :: Scientific/Engineering
Requires-Python: <3.14,>=3.9
License-File: LICENSE
Requires-Dist: appdirs~=1.4
Requires-Dist: importlib_resources<7.0.0,>=6.5.2
Requires-Dist: numpy<3.0.0,>=1.20
Requires-Dist: h5py~=3.8
Requires-Dist: matplotlib>=3.5.2
Requires-Dist: IPython>=7.34.0
Requires-Dist: pyyaml>=6.0
Requires-Dist: xarray>=2022.3.0
Requires-Dist: pint>=0.24.4
Requires-Dist: pint_xarray<=0.6.0,>=0.2.1
Requires-Dist: regex>=2020.7.9
Requires-Dist: packaging>=24.1
Requires-Dist: ontolutils<1.0.0,>=0.25.1
Requires-Dist: python-forge==18.6.0
Requires-Dist: requests>=2.32.4
Requires-Dist: pydantic~=2.8
Requires-Dist: rdflib~=7.1
Requires-Dist: click>=8.1.7
Requires-Dist: cftime>=1.6.4
Requires-Dist: pyshacl<1.0.0,>=0.30.1
Provides-Extra: database
Requires-Dist: pymongo<=4.10.1,>=4.2.0; extra == "database"
Provides-Extra: layout-validation
Requires-Dist: tabulate<=0.9.0,>=0.8.10; extra == "layout-validation"
Provides-Extra: csv
Requires-Dist: pandas>=1.4.3; extra == "csv"
Provides-Extra: snt
Requires-Dist: xmltodict<=0.13.0; extra == "snt"
Requires-Dist: tabulate<=0.9.0,>=0.8.10; extra == "snt"
Requires-Dist: python-gitlab; extra == "snt"
Requires-Dist: pypandoc>=1.11; extra == "snt"
Provides-Extra: gui
Requires-Dist: PyQt5==5.15.10; extra == "gui"
Provides-Extra: test
Requires-Dist: pytest>=8.3.3; extra == "test"
Requires-Dist: pytest-cov>=5.0.0; extra == "test"
Requires-Dist: pylint; extra == "test"
Requires-Dist: ssnolib<3.0.0,>=2.2.0.2; extra == "test"
Requires-Dist: mongomock==4.1.2; extra == "test"
Requires-Dist: xmltodict<=0.13.0; extra == "test"
Requires-Dist: scipy>=1.10.1; extra == "test"
Requires-Dist: scikit-image>=0.21.0; extra == "test"
Requires-Dist: scikit-learn; extra == "test"
Requires-Dist: pandas>=1.4.3; extra == "test"
Requires-Dist: xmltodict<=0.13.0; extra == "test"
Requires-Dist: tabulate<=0.9.0,>=0.8.10; extra == "test"
Requires-Dist: python-gitlab; extra == "test"
Requires-Dist: pypandoc>=1.11; extra == "test"
Requires-Dist: pymongo<=4.10.1,>=4.2.0; extra == "test"
Provides-Extra: docs
Requires-Dist: pandas>=1.4.3; extra == "docs"
Requires-Dist: xmltodict<=0.13.0; extra == "docs"
Requires-Dist: tabulate<=0.9.0,>=0.8.10; extra == "docs"
Requires-Dist: python-gitlab; extra == "docs"
Requires-Dist: pypandoc>=1.11; extra == "docs"
Requires-Dist: pymongo<=4.10.1,>=4.2.0; extra == "docs"
Requires-Dist: pytest>=8.3.3; extra == "docs"
Requires-Dist: pytest-cov>=5.0.0; extra == "docs"
Requires-Dist: pylint; extra == "docs"
Requires-Dist: ssnolib<3.0.0,>=2.2.0.2; extra == "docs"
Requires-Dist: mongomock==4.1.2; extra == "docs"
Requires-Dist: xmltodict<=0.13.0; extra == "docs"
Requires-Dist: scipy>=1.10.1; extra == "docs"
Requires-Dist: scikit-image>=0.21.0; extra == "docs"
Requires-Dist: scikit-learn; extra == "docs"
Requires-Dist: pandas>=1.4.3; extra == "docs"
Requires-Dist: xmltodict<=0.13.0; extra == "docs"
Requires-Dist: tabulate<=0.9.0,>=0.8.10; extra == "docs"
Requires-Dist: python-gitlab; extra == "docs"
Requires-Dist: pypandoc>=1.11; extra == "docs"
Requires-Dist: pymongo<=4.10.1,>=4.2.0; extra == "docs"
Requires-Dist: Sphinx==8.0.0; extra == "docs"
Requires-Dist: sphinx_book_theme==1.1.3; extra == "docs"
Requires-Dist: sphinx-copybutton==0.5.2; extra == "docs"
Requires-Dist: sphinx-design==0.6.1; extra == "docs"
Requires-Dist: myst-nb==1.2.0; extra == "docs"
Requires-Dist: sphinxcontrib-bibtex==2.6.3; extra == "docs"
Requires-Dist: scikit-image>=0.21.0; extra == "docs"
Requires-Dist: scikit-learn; extra == "docs"
Provides-Extra: complete
Requires-Dist: tabulate<=0.9.0,>=0.8.10; extra == "complete"
Requires-Dist: PyQt5==5.15.10; extra == "complete"
Requires-Dist: pytest>=8.3.3; extra == "complete"
Requires-Dist: pytest-cov>=5.0.0; extra == "complete"
Requires-Dist: pylint; extra == "complete"
Requires-Dist: ssnolib<3.0.0,>=2.2.0.2; extra == "complete"
Requires-Dist: mongomock==4.1.2; extra == "complete"
Requires-Dist: xmltodict<=0.13.0; extra == "complete"
Requires-Dist: scipy>=1.10.1; extra == "complete"
Requires-Dist: scikit-image>=0.21.0; extra == "complete"
Requires-Dist: scikit-learn; extra == "complete"
Requires-Dist: pandas>=1.4.3; extra == "complete"
Requires-Dist: xmltodict<=0.13.0; extra == "complete"
Requires-Dist: tabulate<=0.9.0,>=0.8.10; extra == "complete"
Requires-Dist: python-gitlab; extra == "complete"
Requires-Dist: pypandoc>=1.11; extra == "complete"
Requires-Dist: pymongo<=4.10.1,>=4.2.0; extra == "complete"
Provides-Extra: complete-with-docs
Requires-Dist: tabulate<=0.9.0,>=0.8.10; extra == "complete-with-docs"
Requires-Dist: PyQt5==5.15.10; extra == "complete-with-docs"
Requires-Dist: pytest>=8.3.3; extra == "complete-with-docs"
Requires-Dist: pytest-cov>=5.0.0; extra == "complete-with-docs"
Requires-Dist: pylint; extra == "complete-with-docs"
Requires-Dist: ssnolib<3.0.0,>=2.2.0.2; extra == "complete-with-docs"
Requires-Dist: mongomock==4.1.2; extra == "complete-with-docs"
Requires-Dist: xmltodict<=0.13.0; extra == "complete-with-docs"
Requires-Dist: scipy>=1.10.1; extra == "complete-with-docs"
Requires-Dist: scikit-image>=0.21.0; extra == "complete-with-docs"
Requires-Dist: scikit-learn; extra == "complete-with-docs"
Requires-Dist: pandas>=1.4.3; extra == "complete-with-docs"
Requires-Dist: xmltodict<=0.13.0; extra == "complete-with-docs"
Requires-Dist: tabulate<=0.9.0,>=0.8.10; extra == "complete-with-docs"
Requires-Dist: python-gitlab; extra == "complete-with-docs"
Requires-Dist: pypandoc>=1.11; extra == "complete-with-docs"
Requires-Dist: pymongo<=4.10.1,>=4.2.0; extra == "complete-with-docs"
Requires-Dist: pandas>=1.4.3; extra == "complete-with-docs"
Requires-Dist: xmltodict<=0.13.0; extra == "complete-with-docs"
Requires-Dist: tabulate<=0.9.0,>=0.8.10; extra == "complete-with-docs"
Requires-Dist: python-gitlab; extra == "complete-with-docs"
Requires-Dist: pypandoc>=1.11; extra == "complete-with-docs"
Requires-Dist: pymongo<=4.10.1,>=4.2.0; extra == "complete-with-docs"
Requires-Dist: pytest>=8.3.3; extra == "complete-with-docs"
Requires-Dist: pytest-cov>=5.0.0; extra == "complete-with-docs"
Requires-Dist: pylint; extra == "complete-with-docs"
Requires-Dist: ssnolib<3.0.0,>=2.2.0.2; extra == "complete-with-docs"
Requires-Dist: mongomock==4.1.2; extra == "complete-with-docs"
Requires-Dist: xmltodict<=0.13.0; extra == "complete-with-docs"
Requires-Dist: scipy>=1.10.1; extra == "complete-with-docs"
Requires-Dist: scikit-image>=0.21.0; extra == "complete-with-docs"
Requires-Dist: scikit-learn; extra == "complete-with-docs"
Requires-Dist: pandas>=1.4.3; extra == "complete-with-docs"
Requires-Dist: xmltodict<=0.13.0; extra == "complete-with-docs"
Requires-Dist: tabulate<=0.9.0,>=0.8.10; extra == "complete-with-docs"
Requires-Dist: python-gitlab; extra == "complete-with-docs"
Requires-Dist: pypandoc>=1.11; extra == "complete-with-docs"
Requires-Dist: pymongo<=4.10.1,>=4.2.0; extra == "complete-with-docs"
Requires-Dist: Sphinx==8.0.0; extra == "complete-with-docs"
Requires-Dist: sphinx_book_theme==1.1.3; extra == "complete-with-docs"
Requires-Dist: sphinx-copybutton==0.5.2; extra == "complete-with-docs"
Requires-Dist: sphinx-design==0.6.1; extra == "complete-with-docs"
Requires-Dist: myst-nb==1.2.0; extra == "complete-with-docs"
Requires-Dist: sphinxcontrib-bibtex==2.6.3; extra == "complete-with-docs"
Requires-Dist: scikit-image>=0.21.0; extra == "complete-with-docs"
Requires-Dist: scikit-learn; extra == "complete-with-docs"
Dynamic: license-file
